Metadata-Version: 1.1
Name: nose-mongoengine-wait-time
Version: 0.0.1
Summary: A modification for the nose plugin to facilitate the creation of automated tests that access Mongo Engine structures.
Home-page: http://github.com/vanderln/nose-mongoengine/
Author: Bill Van Der Laan
Author-email: wvanderln@hotmail.com
License: BSD-derived
Download-URL: http://github.com/vanderln/nose-mongoengine/tarball/master
Platform: any
Classifier: Environment :: Plugins
Classifier: Intended Audience :: Developers
Classifier: Programming Language :: Python
Classifier: Operating System :: OS Independent
Classifier: Topic :: Internet :: WWW/HTTP
